{
  "products": [
    {
      "id": 1,
      "title": "TSHIRT",
      "price": 100
    },
    {
      "id": 2,
      "title": "PANTS",
      "price": 200
    },
    {
      "id": 3,
      "title": "SHOES",
      "price": 300
    },
    {
      "id": 4,
      "title": "ACCESSORIES",
      "price": 40
    },
    {
      "id": 5,
      "title": "HOODIES",
      "price": 500
    },
    {
      "id": 6,
      "title": "SHIRTS",
      "price": 600
    },
    {
      "id": 7,
      "title": "SHOES",
      "price": 700
    },
    {
      "id": 8,
      "title": "BAGS",
      "price": 800
    },
    {
      "id": 9,
      "title": "HATS",
      "price": 900
    },
    {
      "id": 10,
      "title": "SOCKS",
      "price": 1000
    },
    {
      "id": 11,
      "title": "JOGGERS",
      "price": 1100
    },
    {
      "id": 12,
      "title": "GLOVES",
      "price": 1200
    }
  ],
  "users": [
    {
      "email": "pori@gmail.com",
      "password": "$2a$10$ghV4.FJcSohxyBqkY1eWWOXs6cC95sZ.vAEkDbXlloR89Yv/f5WjW",
      "id": 1
    },
    {
      "email": "alireza@gmail.com",
      "password": "$2a$10$BRV3IcIsvsfDxsignpaGaO2vmsSHUWeGcaH1QS3xFOmmvSn7iOmCm",
      "id": 2
    }
  ]
}